setup.py
lametric/__init__.py
lametric/device.py
lametric/discovery.py
lametric.egg-info/PKG-INFO
lametric.egg-info/SOURCES.txt
lametric.egg-info/dependency_links.txt
lametric.egg-info/requires.txt
lametric.egg-info/top_level.txt